specsynthase/__init__.py
specsynthase/cli.py
specsynthase/specbuilder.py
tests/__init__.py
tests/test_cli.py
tests/test_specsynthase.py
tests/fixtures/petstore/base.yml
tests/fixtures/petstore/definitions.yml
tests/fixtures/petstore/full.yml
tests/fixtures/petstore/paths.yml
tests/fixtures/petstore/security.yml
spec_synthase-0.1.11.dist-info/LICENSE
spec_synthase-0.1.11.dist-info/METADATA
spec_synthase-0.1.11.dist-info/WHEEL
spec_synthase-0.1.11.dist-info/entry_points.txt
spec_synthase-0.1.11.dist-info/top_level.txt
spec_synthase-0.1.11.dist-info/RECORD
