Metadata-Version: 2.1
Name: spec-synthase
Version: 0.1.11
Summary: spec-synthase is a tool to help deal with big swagger files, by building the swagger specification files from little spec files. 
Home-page: https://github.com/MicroarrayTecnologia/spec-synthase
Author: Allan Silva
Author-email: a@allantavares.com.br
License: MPL2
Keywords: OpenAPI Specification,OAS,swagger,yaml,spec,api
Platform: UNKNOWN
Classifier: Intended Audience :: Developers
Classifier: License :: OSI Approved :: Mozilla Public License 2.0 (MPL 2.0)
Classifier: Programming Language :: Python
Classifier: Programming Language :: Python :: 2.7
Classifier: Programming Language :: Python :: 3.5
Classifier: Programming Language :: Python :: 3.6
Classifier: Programming Language :: Python :: 3.7
Requires-Dist: pyyaml
Requires-Dist: swagger-spec-validator
